scale/__init__.py
scale/dataset.py
scale/layer.py
scale/logger.py
scale/loss.py
scale/model.py
scale/plot.py
scale/specifity.py
scale/utils.py
scale_atac-1.1.0.data/scripts/SCALE.py
scale_atac-1.1.0.dist-info/LICENSE
scale_atac-1.1.0.dist-info/METADATA
scale_atac-1.1.0.dist-info/WHEEL
scale_atac-1.1.0.dist-info/top_level.txt
scale_atac-1.1.0.dist-info/RECORD
