Metadata-Version: 2.1
Name: scale-atac
Version: 1.1.0
Summary: Single-Cell ATAC-seq Analysis via Latent feature Extraciton
Home-page: https://github.com/jsxlei/SCALE
Author: Lei Xiong
Author-email: jsxlei@gmail.com
License: MIT
Platform: UNKNOWN
Classifier: Development Status :: 4 - Beta
Classifier: Intended Audience :: Science/Research
Classifier: License :: OSI Approved :: MIT License
Classifier: Programming Language :: Python :: 3.7
Classifier: Operating System :: MacOS :: MacOS X
Classifier: Operating System :: Microsoft :: Windows
Classifier: Operating System :: POSIX :: Linux
Classifier: Topic :: Scientific/Engineering :: Bio-Informatics
Requires-Python: >3.6.0
Requires-Dist: numpy (>=1.14.2)
Requires-Dist: pandas (>=0.22.0)
Requires-Dist: scipy (>=0.19.1)
Requires-Dist: scikit-learn (>=0.19.1)
Requires-Dist: torch (>=1.0.0)
Requires-Dist: tqdm (>=4.28.1)
Requires-Dist: matplotlib (>=3.0.2)
Requires-Dist: seaborn (>=0.9.0)
Requires-Dist: umap-learn
Requires-Dist: scanpy (>=1.6.1)
Requires-Dist: episcanpy (>=0.3.0)
